{"iterations": 0, "train_loss": 2.9071975034825943, "test_loss": 2.8873293540057015, "Accuracy": 0.09191176470588236, "time_this_iter_s": 31.79439687728882, "done": false, "timesteps_total": null, "episodes_total": null, "training_iteration": 1, "trial_id": "6195b59c", "experiment_id": "cb7cd1afa7384e979a4d6dc4d9fb43d9", "date": "2023-01-29_18-46-12", "timestamp": 1675017972, "time_total_s": 31.79439687728882, "pid": 38035, "hostname": "ML-RefVm-847530", "node_ip": "10.0.0.15", "config": {"input": 13, "output": 20, "tunedir": "/home/azureuser/Tentamen/ML22-tentamen/models/tune", "hidden": 132, "num_layers": 2, "dropout": 0.11846541228414063, "batchsize": 88}, "time_since_restore": 31.79439687728882, "timesteps_since_restore": 0, "iterations_since_restore": 1, "warmup_time": 0.004068851470947266}
